thailand_geography/__init__.py
thailand_geography/admin.py
thailand_geography/apps.py
thailand_geography/factories.py
thailand_geography/management/__init__.py
thailand_geography/management/commands/__init__.py
thailand_geography/management/commands/import_geo.py
thailand_geography/migrations/0001_initial.py
thailand_geography/migrations/__init__.py
thailand_geography/models.py
thailand_geography/tests/__init__.py
thailand_geography/tests/test_models.py
thailand_geography/types.py
django_thailand_geography-0.1.4.dist-info/LICENSE
django_thailand_geography-0.1.4.dist-info/METADATA
django_thailand_geography-0.1.4.dist-info/WHEEL
django_thailand_geography-0.1.4.dist-info/RECORD
