Metadata-Version: 2.1
Name: django-thailand-geography
Version: 0.1.4
Summary: 
License: MIT
Keywords: django,thailand,geography,address
Author: Preeti Yuankrathok
Author-email: preetisatit@gmail.com
Requires-Python: >=3.8,<4.0
Classifier: License :: OSI Approved :: MIT License
Classifier: Programming Language :: Python :: 3
Classifier: Programming Language :: Python :: 3.8
Classifier: Programming Language :: Python :: 3.9
Classifier: Programming Language :: Python :: 3.10
Classifier: Programming Language :: Python :: 3.11
Requires-Dist: django (>=3.2)
Requires-Dist: factory-boy (>=3.3.0,<4.0.0)
Requires-Dist: urllib3 (>=2.0.6,<3.0.0)
